{
  "document name": "doc-3.8",
  "tokens": [
    "The",
    "process",
    "starts",
    "when",
    "a",
    "customer",
    "submits",
    "a",
    "claim",
    "by",
    "sending",
    "in",
    "relevant",
    "documentation",
    ".",
    "The",
    "Notification",
    "department",
    "at",
    "the",
    "car",
    "insurer",
    "checks",
    "the",
    "documents",
    "upon",
    "completeness",
    "and",
    "registers",
    "the",
    "claim",
    ".",
    "Then",
    ",",
    "the",
    "Handling",
    "department",
    "picks",
    "up",
    "the",
    "claim",
    "and",
    "checks",
    "the",
    "insurance",
    ".",
    "Then",
    ",",
    "an",
    "assessment",
    "is",
    "performed",
    ".",
    "If",
    "the",
    "assessment",
    "is",
    "positive",
    ",",
    "a",
    "garage",
    "is",
    "phoned",
    "to",
    "authorise",
    "the",
    "repairs",
    "and",
    "the",
    "payment",
    "is",
    "scheduled",
    "(",
    "in",
    "this",
    "order",
    ")",
    ".",
    "Otherwise",
    ",",
    "the",
    "claim",
    "is",
    "rejected",
    ".",
    "In",
    "any",
    "case",
    "(",
    "whether",
    "the",
    "outcome",
    "is",
    "positive",
    "or",
    "negative",
    ")",
    ",",
    "a",
    "letter",
    "is",
    "sent",
    "to",
    "the",
    "customer",
    "and",
    "the",
    "process",
    "is",
    "considered",
    "to",
    "be",
    "complete",
    "."
  ],
  "tokens-IDs": [
    0,
    1,
    2,
    3,
    4,
    5,
    6,
    7,
    8,
    9,
    10,
    11,
    12,
    13,
    14,
    0,
    1,
    2,
    3,
    4,
    5,
    6,
    7,
    8,
    9,
    10,
    11,
    12,
    13,
    14,
    15,
    16,
    0,
    1,
    2,
    3,
    4,
    5,
    6,
    7,
    8,
    9,
    10,
    11,
    12,
    13,
    0,
    1,
    2,
    3,
    4,
    5,
    6,
    0,
    1,
    2,
    3,
    4,
    5,
    6,
    7,
    8,
    9,
    10,
    11,
    12,
    13,
    14,
    15,
    16,
    17,
    18,
    19,
    20,
    21,
    22,
    23,
    24,
    0,
    1,
    2,
    3,
    4,
    5,
    6,
    0,
    1,
    2,
    3,
    4,
    5,
    6,
    7,
    8,
    9,
    10,
    11,
    12,
    13,
    14,
    15,
    16,
    17,
    18,
    19,
    20,
    21,
    22,
    23,
    24,
    25,
    26,
    27,
    28
  ],
  "ner_tags": [
    "O",
    "O",
    "O",
    "O",
    "B-Actor",
    "I-Actor",
    "B-Activity",
    "B-Activity Data",
    "I-Activity Data",
    "B-Further Specification",
    "I-Further Specification",
    "I-Further Specification",
    "I-Further Specification",
    "I-Further Specification",
    "O",
    "B-Actor",
    "I-Actor",
    "I-Actor",
    "O",
    "O",
    "O",
    "O",
    "B-Activity",
    "B-Activity Data",
    "I-Activity Data",
    "B-Further Specification",
    "I-Further Specification",
    "O",
    "B-Activity",
    "B-Activity Data",
    "I-Activity Data",
    "O",
    "O",
    "O",
    "B-Actor",
    "I-Actor",
    "I-Actor",
    "B-Activity",
    "I-Activity",
    "B-Activity Data",
    "I-Activity Data",
    "O",
    "B-Activity",
    "B-Activity Data",
    "I-Activity Data",
    "O",
    "O",
    "O",
    "B-Activity Data",
    "I-Activity Data",
    "O",
    "B-Activity",
    "O",
    "B-XOR Gateway",
    "B-Condition Specification",
    "I-Condition Specification",
    "I-Condition Specification",
    "I-Condition Specification",
    "O",
    "B-Actor",
    "I-Actor",
    "O",
    "B-Activity",
    "B-Further Specification",
    "I-Further Specification",
    "I-Further Specification",
    "I-Further Specification",
    "O",
    "B-Activity Data",
    "I-Activity Data",
    "O",
    "B-Activity",
    "O",
    "O",
    "O",
    "O",
    "O",
    "O",
    "B-XOR Gateway",
    "O",
    "B-Activity Data",
    "I-Activity Data",
    "O",
    "B-Activity",
    "O",
    "O",
    "O",
    "O",
    "O",
    "O",
    "O",
    "O",
    "O",
    "O",
    "O",
    "O",
    "O",
    "O",
    "B-Activity Data",
    "I-Activity Data",
    "O",
    "B-Activity",
    "O",
    "B-Actor",
    "I-Actor",
    "O",
    "O",
    "O",
    "O",
    "O",
    "O",
    "O",
    "O",
    "O"
  ],
  "sentence-IDs": [
    0,
    0,
    0,
    0,
    0,
    0,
    0,
    0,
    0,
    0,
    0,
    0,
    0,
    0,
    0,
    1,
    1,
    1,
    1,
    1,
    1,
    1,
    1,
    1,
    1,
    1,
    1,
    1,
    1,
    1,
    1,
    1,
    2,
    2,
    2,
    2,
    2,
    2,
    2,
    2,
    2,
    2,
    2,
    2,
    2,
    2,
    3,
    3,
    3,
    3,
    3,
    3,
    3,
    4,
    4,
    4,
    4,
    4,
    4,
    4,
    4,
    4,
    4,
    4,
    4,
    4,
    4,
    4,
    4,
    4,
    4,
    4,
    4,
    4,
    4,
    4,
    4,
    4,
    5,
    5,
    5,
    5,
    5,
    5,
    5,
    6,
    6,
    6,
    6,
    6,
    6,
    6,
    6,
    6,
    6,
    6,
    6,
    6,
    6,
    6,
    6,
    6,
    6,
    6,
    6,
    6,
    6,
    6,
    6,
    6,
    6,
    6,
    6,
    6
  ],
  "relations": {
    "source-head-sentence-ID": [
      0,
      0,
      0,
      0,
      1,
      1,
      1,
      1,
      1,
      1,
      1,
      2,
      2,
      2,
      2,
      2,
      2,
      3,
      3,
      4,
      4,
      4,
      4,
      4,
      4,
      4,
      4,
      5,
      5,
      5,
      6,
      6
    ],
    "source-head-word-ID": [
      6,
      6,
      6,
      6,
      7,
      7,
      7,
      7,
      13,
      13,
      13,
      5,
      5,
      5,
      10,
      10,
      10,
      5,
      5,
      0,
      0,
      1,
      9,
      9,
      9,
      18,
      18,
      0,
      5,
      5,
      16,
      16
    ],
    "relation-type": [
      "uses",
      "actor performer",
      "flow",
      "further specification",
      "uses",
      "actor performer",
      "flow",
      "further specification",
      "uses",
      "actor performer",
      "flow",
      "uses",
      "actor performer",
      "flow",
      "uses",
      "actor performer",
      "flow",
      "uses",
      "flow",
      "flow",
      "same gateway",
      "flow",
      "actor recipient",
      "further specification",
      "flow",
      "uses",
      "flow",
      "flow",
      "uses",
      "flow",
      "uses",
      "actor recipient"
    ],
    "target-head-sentence-ID": [
      0,
      0,
      1,
      0,
      1,
      1,
      1,
      1,
      1,
      1,
      2,
      2,
      2,
      2,
      2,
      2,
      3,
      3,
      4,
      4,
      5,
      4,
      4,
      4,
      4,
      4,
      6,
      5,
      5,
      6,
      6,
      6
    ],
    "target-head-word-ID": [
      7,
      4,
      7,
      9,
      8,
      0,
      13,
      10,
      14,
      0,
      5,
      7,
      2,
      10,
      11,
      2,
      5,
      2,
      0,
      1,
      0,
      9,
      6,
      10,
      18,
      15,
      16,
      5,
      2,
      16,
      13,
      18
    ]
  }
}