{
  "document name": "doc-5.2",
  "tokens": [
    "The",
    "process",
    "of",
    "Vacations",
    "Request",
    "starts",
    "when",
    "any",
    "employee",
    "of",
    "the",
    "organization",
    "submits",
    "a",
    "vacation",
    "request",
    ".",
    "Once",
    "the",
    "requirement",
    "is",
    "registered",
    ",",
    "the",
    "request",
    "is",
    "received",
    "by",
    "the",
    "immediate",
    "supervisor",
    "of",
    "the",
    "employee",
    "requesting",
    "the",
    "vacation",
    ".",
    "The",
    "supervisor",
    "must",
    "approve",
    "or",
    "reject",
    "the",
    "request",
    ".",
    "If",
    "the",
    "request",
    "is",
    "rejected",
    ",",
    "the",
    "application",
    "is",
    "returned",
    "to",
    "the",
    "applicant",
    "/",
    "employee",
    "who",
    "can",
    "review",
    "the",
    "rejection",
    "reasons",
    ".",
    "If",
    "the",
    "request",
    "is",
    "approved",
    "a",
    "notification",
    "is",
    "generated",
    "to",
    "the",
    "Human",
    "Resources",
    "Representative",
    ",",
    "who",
    "must",
    "complete",
    "the",
    "respective",
    "management",
    "procedures",
    "."
  ],
  "tokens-IDs": [
    0,
    1,
    2,
    3,
    4,
    5,
    6,
    7,
    8,
    9,
    10,
    11,
    12,
    13,
    14,
    15,
    16,
    0,
    1,
    2,
    3,
    4,
    5,
    6,
    7,
    8,
    9,
    10,
    11,
    12,
    13,
    14,
    15,
    16,
    17,
    18,
    19,
    20,
    0,
    1,
    2,
    3,
    4,
    5,
    6,
    7,
    8,
    0,
    1,
    2,
    3,
    4,
    5,
    6,
    7,
    8,
    9,
    10,
    11,
    12,
    13,
    14,
    15,
    16,
    17,
    18,
    19,
    20,
    21,
    0,
    1,
    2,
    3,
    4,
    5,
    6,
    7,
    8,
    9,
    10,
    11,
    12,
    13,
    14,
    15,
    16,
    17,
    18,
    19,
    20,
    21,
    22
  ],
  "ner_tags": [
    "O",
    "O",
    "O",
    "O",
    "O",
    "O",
    "O",
    "B-Actor",
    "I-Actor",
    "O",
    "O",
    "O",
    "B-Activity",
    "B-Activity Data",
    "I-Activity Data",
    "I-Activity Data",
    "O",
    "O",
    "B-Activity Data",
    "I-Activity Data",
    "O",
    "B-Activity",
    "O",
    "B-Activity Data",
    "I-Activity Data",
    "O",
    "B-Activity",
    "O",
    "B-Actor",
    "I-Actor",
    "I-Actor",
    "O",
    "O",
    "O",
    "O",
    "O",
    "O",
    "O",
    "B-Actor",
    "I-Actor",
    "O",
    "B-Activity",
    "I-Activity",
    "I-Activity",
    "B-Activity Data",
    "I-Activity Data",
    "O",
    "B-XOR Gateway",
    "B-Condition Specification",
    "I-Condition Specification",
    "I-Condition Specification",
    "I-Condition Specification",
    "O",
    "B-Activity Data",
    "I-Activity Data",
    "O",
    "B-Activity",
    "O",
    "B-Actor",
    "I-Actor",
    "I-Actor",
    "I-Actor",
    "O",
    "O",
    "O",
    "O",
    "O",
    "O",
    "O",
    "B-XOR Gateway",
    "B-Condition Specification",
    "I-Condition Specification",
    "I-Condition Specification",
    "I-Condition Specification",
    "B-Activity Data",
    "I-Activity Data",
    "O",
    "B-Activity",
    "O",
    "B-Actor",
    "I-Actor",
    "I-Actor",
    "I-Actor",
    "O",
    "B-Actor",
    "O",
    "B-Activity",
    "B-Activity Data",
    "I-Activity Data",
    "I-Activity Data",
    "I-Activity Data",
    "O"
  ],
  "sentence-IDs": [
    0,
    0,
    0,
    0,
    0,
    0,
    0,
    0,
    0,
    0,
    0,
    0,
    0,
    0,
    0,
    0,
    0,
    1,
    1,
    1,
    1,
    1,
    1,
    1,
    1,
    1,
    1,
    1,
    1,
    1,
    1,
    1,
    1,
    1,
    1,
    1,
    1,
    1,
    2,
    2,
    2,
    2,
    2,
    2,
    2,
    2,
    2,
    3,
    3,
    3,
    3,
    3,
    3,
    3,
    3,
    3,
    3,
    3,
    3,
    3,
    3,
    3,
    3,
    3,
    3,
    3,
    3,
    3,
    3,
    4,
    4,
    4,
    4,
    4,
    4,
    4,
    4,
    4,
    4,
    4,
    4,
    4,
    4,
    4,
    4,
    4,
    4,
    4,
    4,
    4,
    4,
    4
  ],
  "relations": {
    "source-head-sentence-ID": [
      0,
      0,
      0,
      1,
      1,
      1,
      1,
      1,
      2,
      2,
      2,
      3,
      3,
      3,
      3,
      3,
      4,
      4,
      4,
      4,
      4,
      4,
      4
    ],
    "source-head-word-ID": [
      12,
      12,
      12,
      4,
      4,
      9,
      9,
      9,
      3,
      3,
      3,
      0,
      0,
      1,
      9,
      9,
      0,
      1,
      8,
      8,
      8,
      17,
      17
    ],
    "relation-type": [
      "actor performer",
      "flow",
      "uses",
      "uses",
      "flow",
      "uses",
      "flow",
      "actor recipient",
      "uses",
      "actor performer",
      "flow",
      "flow",
      "same gateway",
      "flow",
      "uses",
      "actor recipient",
      "flow",
      "flow",
      "uses",
      "actor recipient",
      "flow",
      "uses",
      "actor performer"
    ],
    "target-head-sentence-ID": [
      0,
      1,
      0,
      1,
      1,
      1,
      2,
      1,
      2,
      2,
      3,
      3,
      4,
      3,
      3,
      3,
      4,
      4,
      4,
      4,
      4,
      4,
      4
    ],
    "target-head-word-ID": [
      7,
      4,
      13,
      1,
      9,
      6,
      3,
      11,
      6,
      0,
      0,
      1,
      0,
      9,
      6,
      11,
      1,
      8,
      5,
      10,
      17,
      18,
      15
    ]
  }
}